LICENSE
README.rst
amsthm/__init__.py
amsthm/helper.py
amsthm/util.py
amsthm-2.0.0.dist-info/entry_points.txt
amsthm-2.0.0.dist-info/LICENSE
amsthm-2.0.0.dist-info/WHEEL
amsthm-2.0.0.dist-info/METADATA
amsthm-2.0.0.dist-info/RECORD
